{
  "$schema": "http://schema.management.azure.com/schemas/2015-01-01/deploymentParameters.json#",
  "contentVersion": "1.0.0.0",
  "parameters": {
    "adminUsername": {
      "value": "laxmiadmin"
    },
    "adminPassword": {
      "value": "Vainavi@123@123"
    },
    "publicDnsName": {
      "value": "laxmidns"
    },
    "mySqlPasswordForRootUser": {
      "value": "Vainavi@123@123"
    },
    "mySqlIdpUser": {
      "value": "lduser"
    },
    "mySqlPasswordForIdpUser": {
      "value": "Vainavi@123@123"
    },
    "numberOfInstances": {
      "value": 1
    }
  }
}
